big5/__init__.py
big5/modules/__init__.py
big5/modules/core/__init__.py
big5/modules/core/core.py
big5/modules/core/exceptions.py
big5/modules/core/language.py
big5/modules/core/messages.py
big5/modules/core/settings.py
big5/modules/lab/__init__.py
big5/modules/lab/audio.py
big5/modules/lab/build.py
big5/modules/lab/download.py
big5/modules/lab/prediction.py
big5/modules/lab/video.py
big5/modules/locales/en/LC_MESSAGES/base.mo
big5/modules/locales/ru/LC_MESSAGES/base.mo
big5-1.0.0a7.dist-info/LICENSE
big5-1.0.0a7.dist-info/METADATA
big5-1.0.0a7.dist-info/WHEEL
big5-1.0.0a7.dist-info/entry_points.txt
big5-1.0.0a7.dist-info/top_level.txt
big5-1.0.0a7.dist-info/RECORD
