Metadata-Version: 2.1
Name: big5
Version: 1.0.0a7
Summary: big5
Home-page: https://github.com/DmitryRyumin/big5
Author: Elena Ryumina, Dmitry Ryumin, Alexey Karpov
Author-email: ryumina_ev@mail.ru, dl_03.03.1991@mail.ru, karpov@iias.spb.su
Maintainer: Elena Ryumina, Dmitry Ryumin
Maintainer-email: ryumina_ev@mail.ru, dl_03.03.1991@mail.ru
License: BSD 3-Clause
Project-URL: Bug Reports, https://github.com/DmitryRyumin/big5/issues
Project-URL: Documentation, https://big5.readthedocs.io
Project-URL: Source Code, https://github.com/DmitryRyumin/big5/tree/main/big5
Project-URL: Download, https://github.com/DmitryRyumin/big5/tags
Keywords: big5,MachineLearning,Statistics,ComputerVision,ArtificialIntelligence,Preprocessing
Platform: UNKNOWN
Classifier: Development Status :: 3 - Alpha
Classifier: Natural Language :: Russian
Classifier: Natural Language :: English
Classifier: Intended Audience :: Developers
Classifier: Intended Audience :: Education
Classifier: Intended Audience :: Science/Research
Classifier: License :: OSI Approved :: BSD License
Classifier: Programming Language :: Python
Classifier: Programming Language :: Python :: 3
Classifier: Programming Language :: Python :: 3.9
Classifier: Programming Language :: Python :: 3 :: Only
Classifier: Programming Language :: Python :: Implementation :: CPython
Classifier: Topic :: Scientific/Engineering
Classifier: Topic :: Scientific/Engineering :: Mathematics
Classifier: Topic :: Scientific/Engineering :: Artificial Intelligence
Classifier: Topic :: Software Development
Classifier: Topic :: Software Development :: Libraries
Classifier: Topic :: Software Development :: Libraries :: Python Modules
Classifier: Operating System :: MacOS :: MacOS X
Classifier: Operating System :: Microsoft :: Windows
Classifier: Operating System :: POSIX :: Linux
Requires-Python: >=3.9, <4
License-File: LICENSE
